{"stationId":52,"pm25SensorIds":[],"pm10SensorIds":[292],"pm25Latest":null,"pm10Latest":10.5,"hasPm25Sensor":false,"hasPm10Sensor":true,"pm25History":[],"pm10History":[{"dateTime":"2026-06-10 02:00:00","value":8},{"dateTime":"2026-06-10 03:00:00","value":10.1},{"dateTime":"2026-06-10 04:00:00","value":13.5},{"dateTime":"2026-06-10 05:00:00","value":23.3},{"dateTime":"2026-06-10 06:00:00","value":39.1},{"dateTime":"2026-06-10 07:00:00","value":53.6},{"dateTime":"2026-06-10 08:00:00","value":71.5},{"dateTime":"2026-06-10 09:00:00","value":39.2},{"dateTime":"2026-06-10 10:00:00","value":14.9},{"dateTime":"2026-06-10 11:00:00","value":7.7},{"dateTime":"2026-06-10 12:00:00","value":7.9},{"dateTime":"2026-06-10 13:00:00","value":8.3},{"dateTime":"2026-06-10 14:00:00","value":7},{"dateTime":"2026-06-10 15:00:00","value":7},{"dateTime":"2026-06-10 16:00:00","value":4.3},{"dateTime":"2026-06-10 17:00:00","value":2.6},{"dateTime":"2026-06-10 18:00:00","value":3},{"dateTime":"2026-06-10 19:00:00","value":3.8},{"dateTime":"2026-06-10 20:00:00","value":6.5},{"dateTime":"2026-06-10 21:00:00","value":8},{"dateTime":"2026-06-10 22:00:00","value":9.8},{"dateTime":"2026-06-10 23:00:00","value":6.5},{"dateTime":"2026-06-11 00:00:00","value":6.5},{"dateTime":"2026-06-11 01:00:00","value":9},{"dateTime":"2026-06-11 02:00:00","value":7.7},{"dateTime":"2026-06-11 03:00:00","value":4.1},{"dateTime":"2026-06-11 04:00:00","value":2.8},{"dateTime":"2026-06-11 05:00:00","value":3.3},{"dateTime":"2026-06-11 06:00:00","value":8.6},{"dateTime":"2026-06-11 07:00:00","value":12.1},{"dateTime":"2026-06-11 14:00:00","value":8.8},{"dateTime":"2026-06-11 15:00:00","value":14.6},{"dateTime":"2026-06-11 16:00:00","value":11.2},{"dateTime":"2026-06-11 17:00:00","value":8.7},{"dateTime":"2026-06-11 18:00:00","value":10.7},{"dateTime":"2026-06-11 19:00:00","value":12.5},{"dateTime":"2026-06-11 21:00:00","value":16.1},{"dateTime":"2026-06-11 22:00:00","value":16.9},{"dateTime":"2026-06-11 23:00:00","value":17.1},{"dateTime":"2026-06-12 00:00:00","value":16.8},{"dateTime":"2026-06-12 01:00:00","value":18.8},{"dateTime":"2026-06-12 02:00:00","value":19.4},{"dateTime":"2026-06-12 03:00:00","value":5.4},{"dateTime":"2026-06-12 04:00:00","value":11.2},{"dateTime":"2026-06-12 05:00:00","value":17.6},{"dateTime":"2026-06-12 06:00:00","value":22.5},{"dateTime":"2026-06-12 07:00:00","value":31.8},{"dateTime":"2026-06-12 08:00:00","value":30.7},{"dateTime":"2026-06-12 09:00:00","value":21.6},{"dateTime":"2026-06-12 10:00:00","value":10.5}]}